weberFuncs/CConfigRun.py
weberFuncs/CDeferFuncThread.py
weberFuncs/CHandleCmd_BaseService.py
weberFuncs/CHandleCmd_TstBasic.py
weberFuncs/CHttpJsonClient.py
weberFuncs/CLogTagMsg.py
weberFuncs/CNameValueCsv.py
weberFuncs/CPickleDict.py
weberFuncs/CRunCronTask.py
weberFuncs/CSendCustomMsgWX.py
weberFuncs/CSendSMTPMail.py
weberFuncs/CSerialJson.py
weberFuncs/CmdStrFuncs.py
weberFuncs/ExecCmdFuns.py
weberFuncs/JsonRpcFuncs.py
weberFuncs/PrettyPrint.py
weberFuncs/SimpleShiftEncDec.py
weberFuncs/WyfCryptoFuncs.py
weberFuncs/WyfEasyFuncs.py
weberFuncs/WyfHttpFuncs.py
weberFuncs/WyfPublicFuncs.py
weberFuncs/WyfQueueThread.py
weberFuncs/WyfSupplyFuncs.py
weberFuncs/__init__.py
weberFuncs/dict_name_value_file.py
weberFuncs/python_version.py
weberfuncs-0.0.171.dist-info/licenses/LICENSE
weberfuncs-0.0.171.dist-info/METADATA
weberfuncs-0.0.171.dist-info/WHEEL
weberfuncs-0.0.171.dist-info/top_level.txt
weberfuncs-0.0.171.dist-info/RECORD
