Metadata-Version: 2.4
Name: weberFuncs
Version: 0.0.171
Summary: Public functions library wrote by Weber Juche.
Home-page: https://github.com/Weber-JC/PythonEggs/tree/master/weberFuncs
Author: Weber Juche
Author-email: weber.juche@gmail.com
License: MIT
Keywords: public weberFuncs weber
Classifier: License :: OSI Approved :: MIT License
Classifier: Programming Language :: Python
Classifier: Intended Audience :: Developers
Classifier: Operating System :: OS Independent
License-File: LICENSE
Requires-Dist: schedule
Dynamic: author
Dynamic: author-email
Dynamic: classifier
Dynamic: description
Dynamic: home-page
Dynamic: keywords
Dynamic: license
Dynamic: license-file
Dynamic: requires-dist
Dynamic: summary
